{
    "data" :
    [
        {
            "id" : "cti",
            "name" : "中天新聞",
            "embed_code" : "VsvZqiB2y1o",
            "url" : "http://www.ctitv.com.tw/"
        },
        {
            "id" : "cts",
            "name" : "華視新聞",
            "embed_code" : "1I6fxNSmQh4",
            "url" : "http://news.cts.com.tw/"
        },
        {
            "id" : "ctv",
            "name" : "中視新聞",
            "embed_code" : "Ip65uIIj0n4",
            "url" : "http://www.ctv.com.tw/opencms/jsp/index_2.jsp"
        },
        {
            "id" : "ebc",
            "name" : "東森新聞",
            "embed_code" : "5M7czC0VR_Q",
            "url" : "http://www.ettoday.net/"
        },
        {
            "id" : "ebc_f",
            "name" : "東森財經",
            "embed_code" : "377TfbJ1Yus",
            "url" : "http://fnc.ebc.net.tw/apps/index.aspx"
        },
        {
            "id" : "ftv",
            "name" : "民視新聞",
            "embed_code" : "XxJKnDLYZz4",
            "url" : "http://news.ftv.com.tw/"
        },
        {
            "id" : "set",
            "name" : "三立新聞",
            "embed_code" : "cEE6Lh1WBp0",
            "url" : "http://www.setn.com/"
        },
        {
            "id" : "set_f",
            "name" : "三立財經",
            "embed_code" : "A5jGXvZsfxM",
            "url" : "http://www.setn.com/"
        },
        {
            "id" : "ttv",
            "name" : "台視新聞",
            "embed_code" : "yk2CUjbyyQY",
            "url" : "http://www.ttv.com.tw/news/"
        }
    ]
}